LICENSE
README.md
ytdld.py
ytdld-0.0.3.dist-info/LICENSE
ytdld-0.0.3.dist-info/METADATA
ytdld-0.0.3.dist-info/WHEEL
ytdld-0.0.3.dist-info/entry_points.txt
ytdld-0.0.3.dist-info/RECORD
