Metadata-Version: 2.1
Name: ytdld
Version: 0.0.3
Summary: Just another youtube downloader
Home-page: https://github.com/KasRoudra/ytdld/
License: MIT
Author: KasRoudra
Author-email: kasroudrakrd@gmail.com
Requires-Python: >=3.9,<4.0
Classifier: License :: OSI Approved :: MIT License
Classifier: Programming Language :: Python :: 3
Classifier: Programming Language :: Python :: 3.9
Classifier: Programming Language :: Python :: 3.10
Classifier: Programming Language :: Python :: 3.11
Requires-Dist: pytube (>=15.0.0,<16.0.0)
Requires-Dist: questionary (>=1.10.0,<2.0.0)
Project-URL: Repository, https://github.com/KasRoudra/ytdld/
